logentry/__init__.py
logentry/admin.py
logentry/apps.py
logentry/models.py
logentry/signals.py
logentry/tests.py
logentry/views.py
logentry/migrations/0001_initial.py
logentry/migrations/0002_auto_20170606_0045.py
logentry/migrations/__init__.py
logentry-1.0.0.dist-info/DESCRIPTION.rst
logentry-1.0.0.dist-info/METADATA
logentry-1.0.0.dist-info/RECORD
logentry-1.0.0.dist-info/WHEEL
logentry-1.0.0.dist-info/metadata.json
logentry-1.0.0.dist-info/top_level.txt
